chemeq/__init__.py
chemeq/count_elements.py
chemeq/equation_balancer.py
chemeq/syntax_review.py
chemeq-0.1.7.dist-info/LICENSE.txt
chemeq-0.1.7.dist-info/METADATA
chemeq-0.1.7.dist-info/WHEEL
chemeq-0.1.7.dist-info/top_level.txt
chemeq-0.1.7.dist-info/RECORD
