Metadata-Version: 2.1
Name: chemeq
Version: 0.1.7
Summary: Balance chemical equations & calculates molecular weights plus periodic table of elements
Home-page: https://github.com/elbiop/chemeq
Author: Elbio Peña
Author-email: elbioemilio@outlook.es
Keywords: chemistry,chemical,chemicals,equation,equations,balance,balancer,balancing,reaction,reactions,periodic table,elements
Classifier: Development Status :: 5 - Production/Stable
Classifier: Programming Language :: Python :: 3
Classifier: Operating System :: OS Independent
Classifier: Intended Audience :: Education
Classifier: Intended Audience :: End Users/Desktop
Requires-Python: >= 3.6
License-File: LICENSE.txt
Requires-Dist: numpy
Requires-Dist: pandas
